<ipe version="60028" creator="Ipe 6.0 preview 28">
<info created="D:20080423150950" modified="D:20080425102947" bbox="cropbox"/>
<ipestyle>
</ipestyle>
<page gridsize="16">
<layer name="alpha"/>
<view layers="alpha" active="alpha"/>
<path layer="alpha" stroke="black" matrix="0.7 0 0 0.7 89.3425 65.7859" pen="normal">
247.275 214.852 m
207.63 91.7751
381.003 103.018
444.317 216.627
341.358 258.047 s
</path>
<path stroke="black" matrix="0.7 0 0 0.7 89.3425 65.7859" pen="normal">
341.358 258.047 m
361.476 323.728
195.204 340.888
265.027 289.408
140.175 228.462
189.879 180.533
247.275 214.852 s
</path>
<mark stroke="black" matrix="0.7 0 0 0.7 89.3425 65.7859" pos="247.275 214.852" shape="2" size="normal" pen="normal"/>
<mark stroke="black" matrix="0.7 0 0 0.7 89.3425 65.7859" pos="341.358 258.047" shape="2" size="normal" pen="normal"/>
<path stroke="black" matrix="0.7 0 0 0.7 89.3425 65.7859" pen="normal">
235.53 177.293 m
377.653 242.544 l
</path>
<path stroke="black" matrix="0.7 0 0 0.7 89.3425 65.7859" pen="normal">
392.931 249.559 m
392.931 249.559 l
</path>
<mark stroke="black" matrix="0.7 0 0 0.7 89.3425 65.7859" pos="235.53 177.293" shape="2" size="normal" pen="normal"/>
<mark stroke="black" matrix="0.7 0 0 0.7 89.3425 65.7859" pos="377.653 242.544" shape="2" size="normal" pen="normal"/>
<text stroke="black" matrix="0.7 0 0 0.7 93.4846 64.9575" pos="238.399 220.178" type="label" width="8.9641" height="4.2938" depth="1.49" valign="baseline" size="normal">$r_1$</text>
<text stroke="black" matrix="0.7 0 0 0.7 90.9993 61.6439" pos="325.382 263.373" type="label" width="8.9641" height="4.2938" depth="1.49" valign="baseline" size="normal">$r_2$</text>
<text stroke="black" matrix="0.7 0 0 0.7 92.6561 68.6854" pos="215.914 168.698" type="label" width="8.9641" height="7.4926" depth="2.47" valign="baseline" size="normal">$r_1'$</text>
<text stroke="black" matrix="0.7 0 0 0.7 83.5437 61.6439" pos="392.931 249.559" type="label" width="8.9641" height="7.4926" depth="2.47" valign="baseline" size="normal">$r_2'$</text>
<text stroke="black" matrix="0.7 0 0 0.7 82.3011 49.6321" pos="350.234 337.929" type="label" width="10.6711" height="7.4969" depth="1.93" valign="baseline" size="normal">$Q'$</text>
<text stroke="black" matrix="0.7 0 0 0.7 90.5851 57.0877" pos="418.873 217.811" type="label" width="10.5749" height="7.4897" depth="0" valign="baseline" size="normal">$P'$</text>
<path stroke="black" matrix="0.7 0 0 0.7 89.3425 65.7859" pen="normal">
264.435 336.746 m
264.435 336.746 l
</path>
<path stroke="black" matrix="0.7 0 0 0.7 89.3425 65.7859" pen="normal">
234.188 292.26 m
377.367 129.192 l
</path>
<text stroke="black" matrix="0.7 0 0 0.7 88.0999 59.1587" pos="268.577 270.473" type="label" width="10.6282" height="6.8122" depth="1.49" valign="baseline" size="normal">$C_t$</text>
<mark stroke="black" matrix="0.7 0 0 0.7 89.3425 65.7859" pos="306.517 209.884" shape="2" size="normal" pen="normal"/>
<text stroke="black" matrix="0.7 0 0 0.7 90.5851 67.4428" pos="300.53 192.959" type="label" width="7.9551" height="4.2966" depth="1.93" valign="baseline" size="normal">$q_t$</text>
</page>
</ipe>
