<ipe version="60030" creator="Ipe 6.0 preview 30">
<info created="D:20090807160845" modified="D:20090807160845" bbox="cropbox"/>
<page gridsize="16">
<layer name="alpha"/>
<view layers="alpha" active="alpha"/>
<path layer="alpha" stroke="black" matrix="1 0 0 1 0 2.04852" pen="normal">
88.6466 187.033 m
283.913 187.033 l
283.913 394.133 l
88.6466 394.133 l
h
</path>
<group>
<path stroke="black" matrix="1 0 0 1 0 -10.0137" pen="normal">
88.6466 313.569 m
283.913 313.569 l
</path>
<path stroke="black" matrix="1 0 0 1 0 -10.0137" pen="normal">
88.6466 291.721 m
283.913 291.721 l
</path>
<path stroke="white" matrix="1 0 0 1 17.2963 -10.0137" pen="heavier">
142.356 313.569 m
145.542 313.569 l
</path>
<path stroke="white" matrix="1 0 0 1 29.1308 -10.0137" pen="heavier">
142.356 313.569 m
145.542 313.569 l
</path>
<path stroke="white" matrix="1 0 0 1 29.1308 -10.0137" pen="heavier">
142.356 313.569 m
145.542 313.569 l
</path>
<path stroke="white" matrix="1 0 0 1 40.9653 -10.0137" pen="heavier">
142.356 313.569 m
145.542 313.569 l
</path>
<path stroke="white" matrix="1 0 0 1 40.9651 -10.0134" pen="heavier">
142.356 313.569 m
145.542 313.569 l
</path>
<path stroke="white" matrix="1 0 0 1 52.7996 -10.0134" pen="heavier">
142.356 313.569 m
145.542 313.569 l
</path>
<path stroke="white" matrix="1 0 0 1 52.7996 -10.0134" pen="heavier">
142.356 313.569 m
145.542 313.569 l
</path>
<path stroke="white" matrix="1 0 0 1 64.6341 -10.0134" pen="heavier">
142.356 313.569 m
145.542 313.569 l
</path>
<path stroke="white" matrix="1 0 0 1 17.2963 -31.8616" pen="heavier">
142.356 313.569 m
145.542 313.569 l
</path>
<path stroke="white" matrix="1 0 0 1 29.1308 -31.8616" pen="heavier">
142.356 313.569 m
145.542 313.569 l
</path>
<path stroke="white" matrix="1 0 0 1 29.1308 -31.8616" pen="heavier">
142.356 313.569 m
145.542 313.569 l
</path>
<path stroke="white" matrix="1 0 0 1 40.9653 -31.8616" pen="heavier">
142.356 313.569 m
145.542 313.569 l
</path>
<path stroke="white" matrix="1 0 0 1 40.9651 -31.8614" pen="heavier">
142.356 313.569 m
145.542 313.569 l
</path>
<path stroke="white" matrix="1 0 0 1 52.7996 -31.8614" pen="heavier">
142.356 313.569 m
145.542 313.569 l
</path>
<path stroke="white" matrix="1 0 0 1 52.7996 -31.8614" pen="heavier">
142.356 313.569 m
145.542 313.569 l
</path>
<path stroke="white" matrix="1 0 0 1 64.6341 -31.8614" pen="heavier">
142.356 313.569 m
145.542 313.569 l
</path>
</group>
</page>
</ipe>
