<?xml version="1.0"?>
<!DOCTYPE ipe SYSTEM "ipe.dtd">
<ipe version="70005" creator="Ipe 7.1.1">
<info created="D:20130121144924" modified="D:20130125084630"/>
<ipestyle name="basic">
<symbol name="arrow/arc(spx)">
<path stroke="sym-stroke" fill="sym-stroke" pen="sym-pen">
0 0 m
-1 0.333 l
-1 -0.333 l
h
</path>
</symbol>
<symbol name="arrow/farc(spx)">
<path stroke="sym-stroke" fill="white" pen="sym-pen">
0 0 m
-1 0.333 l
-1 -0.333 l
h
</path>
</symbol>
<symbol name="mark/circle(sx)" transformations="translations">
<path fill="sym-stroke">
0.6 0 0 0.6 0 0 e
0.4 0 0 0.4 0 0 e
</path>
</symbol>
<symbol name="mark/disk(sx)" transformations="translations">
<path fill="sym-stroke">
0.6 0 0 0.6 0 0 e
</path>
</symbol>
<symbol name="mark/fdisk(sfx)" transformations="translations">
<group>
<path fill="sym-fill">
0.5 0 0 0.5 0 0 e
</path>
<path fill="sym-stroke" fillrule="eofill">
0.6 0 0 0.6 0 0 e
0.4 0 0 0.4 0 0 e
</path>
</group>
</symbol>
<symbol name="mark/box(sx)" transformations="translations">
<path fill="sym-stroke" fillrule="eofill">
-0.6 -0.6 m
0.6 -0.6 l
0.6 0.6 l
-0.6 0.6 l
h
-0.4 -0.4 m
0.4 -0.4 l
0.4 0.4 l
-0.4 0.4 l
h
</path>
</symbol>
<symbol name="mark/square(sx)" transformations="translations">
<path fill="sym-stroke">
-0.6 -0.6 m
0.6 -0.6 l
0.6 0.6 l
-0.6 0.6 l
h
</path>
</symbol>
<symbol name="mark/fsquare(sfx)" transformations="translations">
<group>
<path fill="sym-fill">
-0.5 -0.5 m
0.5 -0.5 l
0.5 0.5 l
-0.5 0.5 l
h
</path>
<path fill="sym-stroke" fillrule="eofill">
-0.6 -0.6 m
0.6 -0.6 l
0.6 0.6 l
-0.6 0.6 l
h
-0.4 -0.4 m
0.4 -0.4 l
0.4 0.4 l
-0.4 0.4 l
h
</path>
</group>
</symbol>
<symbol name="mark/cross(sx)" transformations="translations">
<group>
<path fill="sym-stroke">
-0.43 -0.57 m
0.57 0.43 l
0.43 0.57 l
-0.57 -0.43 l
h
</path>
<path fill="sym-stroke">
-0.43 0.57 m
0.57 -0.43 l
0.43 -0.57 l
-0.57 0.43 l
h
</path>
</group>
</symbol>
<symbol name="arrow/fnormal(spx)">
<path stroke="sym-stroke" fill="white" pen="sym-pen">
0 0 m
-1 0.333 l
-1 -0.333 l
h
</path>
</symbol>
<symbol name="arrow/pointed(spx)">
<path stroke="sym-stroke" fill="sym-stroke" pen="sym-pen">
0 0 m
-1 0.333 l
-0.8 0 l
-1 -0.333 l
h
</path>
</symbol>
<symbol name="arrow/fpointed(spx)">
<path stroke="sym-stroke" fill="white" pen="sym-pen">
0 0 m
-1 0.333 l
-0.8 0 l
-1 -0.333 l
h
</path>
</symbol>
<symbol name="arrow/linear(spx)">
<path stroke="sym-stroke" pen="sym-pen">
-1 0.333 m
0 0 l
-1 -0.333 l
</path>
</symbol>
<symbol name="arrow/fdouble(spx)">
<path stroke="sym-stroke" fill="white" pen="sym-pen">
0 0 m
-1 0.333 l
-1 -0.333 l
h
-1 0 m
-2 0.333 l
-2 -0.333 l
h
</path>
</symbol>
<symbol name="arrow/double(spx)">
<path stroke="sym-stroke" fill="sym-stroke" pen="sym-pen">
0 0 m
-1 0.333 l
-1 -0.333 l
h
-1 0 m
-2 0.333 l
-2 -0.333 l
h
</path>
</symbol>
<pen name="heavier" value="0.8"/>
<pen name="fat" value="1.2"/>
<pen name="ultrafat" value="2"/>
<symbolsize name="large" value="5"/>
<symbolsize name="small" value="2"/>
<symbolsize name="tiny" value="1.1"/>
<arrowsize name="large" value="10"/>
<arrowsize name="small" value="5"/>
<arrowsize name="tiny" value="3"/>
<color name="red" value="1 0 0"/>
<color name="green" value="0 1 0"/>
<color name="blue" value="0 0 1"/>
<color name="yellow" value="1 1 0"/>
<color name="orange" value="1 0.647 0"/>
<color name="gold" value="1 0.843 0"/>
<color name="purple" value="0.627 0.125 0.941"/>
<color name="gray" value="0.745"/>
<color name="brown" value="0.647 0.165 0.165"/>
<color name="navy" value="0 0 0.502"/>
<color name="pink" value="1 0.753 0.796"/>
<color name="seagreen" value="0.18 0.545 0.341"/>
<color name="turquoise" value="0.251 0.878 0.816"/>
<color name="violet" value="0.933 0.51 0.933"/>
<color name="darkblue" value="0 0 0.545"/>
<color name="darkcyan" value="0 0.545 0.545"/>
<color name="darkgray" value="0.663"/>
<color name="darkgreen" value="0 0.392 0"/>
<color name="darkmagenta" value="0.545 0 0.545"/>
<color name="darkorange" value="1 0.549 0"/>
<color name="darkred" value="0.545 0 0"/>
<color name="lightblue" value="0.678 0.847 0.902"/>
<color name="lightcyan" value="0.878 1 1"/>
<color name="lightgray" value="0.827"/>
<color name="lightgreen" value="0.565 0.933 0.565"/>
<color name="lightyellow" value="1 1 0.878"/>
<dashstyle name="dashed" value="[4] 0"/>
<dashstyle name="dotted" value="[1 3] 0"/>
<dashstyle name="dash dotted" value="[4 2 1 2] 0"/>
<dashstyle name="dash dot dotted" value="[4 2 1 2 1 2] 0"/>
<textsize name="large" value="\large"/>
<textsize name="small" value="\small"/>
<textsize name="tiny" value="\tiny"/>
<textsize name="Large" value="\Large"/>
<textsize name="LARGE" value="\LARGE"/>
<textsize name="huge" value="\huge"/>
<textsize name="Huge" value="\Huge"/>
<textsize name="footnote" value="\footnotesize"/>
<textstyle name="center" begin="\begin{center}" end="\end{center}"/>
<textstyle name="itemize" begin="\begin{itemize}" end="\end{itemize}"/>
<textstyle name="item" begin="\begin{itemize}\item{}" end="\end{itemize}"/>
<gridsize name="4 pts" value="4"/>
<gridsize name="8 pts (~3 mm)" value="8"/>
<gridsize name="16 pts (~6 mm)" value="16"/>
<gridsize name="32 pts (~12 mm)" value="32"/>
<gridsize name="10 pts (~3.5 mm)" value="10"/>
<gridsize name="20 pts (~7 mm)" value="20"/>
<gridsize name="14 pts (~5 mm)" value="14"/>
<gridsize name="28 pts (~10 mm)" value="28"/>
<gridsize name="56 pts (~20 mm)" value="56"/>
<anglesize name="90 deg" value="90"/>
<anglesize name="60 deg" value="60"/>
<anglesize name="45 deg" value="45"/>
<anglesize name="30 deg" value="30"/>
<anglesize name="22.5 deg" value="22.5"/>
<tiling name="falling" angle="-60" step="4" width="1"/>
<tiling name="rising" angle="30" step="4" width="1"/>
</ipestyle>
<page>
<layer name="alpha"/>
<layer name="beta"/>
<view layers="alpha" active="alpha"/>
<group layer="alpha">
<path stroke="darkgray" fill="lightcyan">
414.206 645.874 m
402.837 695.686 l
368.172 668.042 l
h
</path>
<path matrix="0.6 0 0 0.6 312.655 259.121" stroke="darkgray">
169.252 644.587 m
248.028 743.37 l
</path>
<path matrix="0.6 0 0 0.6 312.655 259.121" stroke="darkgray">
169.252 644.587 m
141.137 767.767 l
</path>
<path matrix="0.6 0 0 0.6 312.655 259.121" stroke="darkgray">
169.252 644.587 m
55.4161 699.407 l
</path>
<path matrix="0.6 0 0 0.6 312.655 259.121" stroke="darkgray">
169.252 644.587 m
55.4161 589.767 l
</path>
<path matrix="0.6 0 0 0.6 312.655 259.121" stroke="darkgray">
169.252 644.587 m
141.137 521.407 l
</path>
<path matrix="0.6 0 0 0.6 312.655 259.121" stroke="darkgray">
169.252 644.587 m
248.028 545.804 l
</path>
<path matrix="0.6 0 0 0.6 312.655 259.121" stroke="darkgray">
169.252 644.587 m
295.599 644.587 l
</path>
<path stroke="darkgray" fill="lightcyan">
414.206 645.874 m
389.853 657.602 l
389.853 634.146 l
h
</path>
<path stroke="darkgray" fill="lightcyan">
414.206 645.874 m
376.32 627.629 l
404.849 604.878 l
h
</path>
<path stroke="darkgray" fill="lightcyan">
414.206 645.874 m
403.196 597.634 l
445.057 607.188 l
h
</path>
<path stroke="darkgray" fill="lightcyan">
414.206 645.874 m
443.171 609.552 l
460.663 645.874 l
h
</path>
<path stroke="darkgray" fill="lightcyan">
414.206 645.874 m
446.504 645.874 l
434.344 671.125 l
h
</path>
</group>
<path stroke="darkgray" fill="lightcyan">
414.206 645.874 m
452.417 693.788 l
400.569 705.622 l
h
</path>
<use matrix="0.6 0 0 0.6 292.105 234.004" name="mark/disk(sx)" pos="203.502 686.449" size="normal" stroke="black"/>
<use name="mark/disk(sx)" pos="438.989 661.48" size="normal" stroke="black"/>
<use name="mark/disk(sx)" pos="433.615 698.08" size="normal" stroke="black"/>
<use name="mark/disk(sx)" pos="387.969 683.829" size="normal" stroke="black"/>
<use name="mark/disk(sx)" pos="389.853 649.129" size="normal" stroke="black"/>
<use name="mark/disk(sx)" pos="392.543 614.692" size="normal" stroke="black"/>
<use name="mark/disk(sx)" pos="419.551 601.367" size="normal" stroke="black"/>
<use name="mark/disk(sx)" pos="451.282 626.394" size="normal" stroke="black"/>
<path stroke="black" fill="lightcyan">
414.206 645.874 m
433.615 698.08 l
</path>
<path stroke="black" fill="lightcyan">
414.206 645.874 m
438.989 661.48 l
</path>
<path stroke="black" fill="lightcyan">
414.206 645.874 m
387.969 683.829 l
</path>
<path stroke="black" fill="lightcyan">
414.206 645.874 m
389.853 649.129 l
</path>
<path stroke="black" fill="lightcyan">
414.206 645.874 m
392.543 614.692 l
</path>
<path stroke="black" fill="lightcyan">
414.206 645.874 m
419.551 601.367 l
</path>
<path stroke="black" fill="lightcyan">
414.206 645.874 m
451.282 626.394 l
</path>
<use name="mark/disk(sx)" pos="364.057 683.777" size="normal" stroke="black"/>
<use name="mark/disk(sx)" pos="385.666 690.723" size="normal" stroke="black"/>
<use name="mark/disk(sx)" pos="447.79 715.804" size="normal" stroke="black"/>
<use name="mark/disk(sx)" pos="452.034 677.217" size="normal" stroke="black"/>
<use name="mark/disk(sx)" pos="446.246 660.239" size="normal" stroke="black"/>
<use name="mark/disk(sx)" pos="463.61 630.528" size="normal" stroke="black"/>
<use name="mark/disk(sx)" pos="453.578 613.164" size="normal" stroke="black"/>
<use name="mark/disk(sx)" pos="431.198 596.957" size="normal" stroke="black"/>
<use name="mark/disk(sx)" pos="375.633 619.338" size="normal" stroke="black"/>
<use name="mark/disk(sx)" pos="392.997 587.697" size="normal" stroke="black"/>
<use name="mark/disk(sx)" pos="366.758 648.277" size="normal" stroke="black"/>
<use name="mark/disk(sx)" pos="357.497 628.984" size="normal" stroke="black"/>
<use name="mark/disk(sx)" pos="355.568 659.082" size="normal" stroke="black"/>
<text matrix="1 0 0 1 -2.71956 -3.6794" transformations="translations" pos="413.08 656.751" stroke="black" type="label" width="5.703" height="4.289" depth="0" valign="baseline">$u$</text>
<group layer="beta" matrix="0.900969 0.433884 -0.433884 0.900969 321.253 -115.756">
<path stroke="black">
66.8633 0 0 66.8633 414.206 645.873 e
</path>
<path stroke="black">
481.069 645.873 m
455.895 698.149 l
399.328 711.06 l
353.964 674.884 l
353.964 616.862 l
399.328 580.686 l
455.895 593.597 l
h
</path>
</group>
<text layer="alpha" transformations="translations" pos="474.448 674.884" stroke="black" type="label" width="29.47" height="6.812" depth="1.49" halign="center" valign="center">$C_1+u$</text>
<text matrix="1 0 0 1 -45.3633 36.1761" transformations="translations" pos="474.448 674.884" stroke="black" type="label" width="29.47" height="6.812" depth="1.49" halign="center" valign="center">$C_2+u$</text>
<text matrix="1 0 0 1 -101.93 23.265" transformations="translations" pos="474.448 674.884" stroke="black" type="label" width="29.47" height="6.812" depth="1.49" halign="center" valign="center">$C_3+u$</text>
<text matrix="1 0 0 1 -127.105 -29.0108" transformations="translations" pos="474.448 674.884" stroke="black" type="label" width="29.47" height="6.812" depth="1.49" halign="center" valign="center">$C_4+u$</text>
<text matrix="1 0 0 1 -101.93 -81.2866" transformations="translations" pos="474.448 674.884" stroke="black" type="label" width="29.47" height="6.812" depth="1.49" halign="center" valign="center">$C_5+u$</text>
<text matrix="1 0 0 1 -45.3633 -94.1977" transformations="translations" pos="474.448 674.884" stroke="black" type="label" width="29.47" height="6.812" depth="1.49" halign="center" valign="center">$C_6+u$</text>
<text matrix="1 0 0 1 -0.00007116 -58.0217" transformations="translations" pos="474.448 674.884" stroke="black" type="label" width="29.47" height="6.812" depth="1.49" halign="center" valign="center">$C_7+u$</text>
</page>
</ipe>
